splight_cli/__init__.py
splight_cli/cli.py
splight_cli/constants.py
splight_cli/version.py
splight_cli/component/__init__.py
splight_cli/component/component.py
splight_cli/component/exceptions.py
splight_cli/component/loaders.py
splight_cli/component/utils.py
splight_cli/component/templates/.splightignore
splight_cli/component/templates/Initialization
splight_cli/component/templates/README.md
splight_cli/component/templates/auto_readme.md
splight_cli/component/templates/main.py
splight_cli/component/templates/spec.json
splight_cli/component/templates/tests.py
splight_cli/component/tests/__init__.py
splight_cli/component/tests/test_component_manager.py
splight_cli/config/__init__.py
splight_cli/engine/__init__.py
splight_cli/engine/alert/__init__.py
splight_cli/engine/asset/__init__.py
splight_cli/engine/attribute/__init__.py
splight_cli/engine/component/__init__.py
splight_cli/engine/datalake/__init__.py
splight_cli/engine/file/__init__.py
splight_cli/engine/manager/__init__.py
splight_cli/engine/manager/exceptions.py
splight_cli/engine/manager/manager.py
splight_cli/engine/manager/tests/test_datalake_manager.py
splight_cli/engine/manager/tests/test_resource_manager.py
splight_cli/engine/secret/__init__.py
splight_cli/tests/test_component/Initialization
splight_cli/tests/test_component/README.md
splight_cli/tests/test_component/main.py
splight_cli/tests/test_component/spec.json
splight_cli/tests/test_component/tests.py
splight_cli/utils/__init__.py
splight_cli/utils/input.py
splight_cli/utils/json.py
splight_cli/utils/loader.py
splight_cli/utils/pprint.py
splight_cli/utils/template.py
splight_cli/utils/yaml.py
splight_cli/workspace/__init__.py
splight_cli-5.6.2.dist-info/METADATA
splight_cli-5.6.2.dist-info/WHEEL
splight_cli-5.6.2.dist-info/entry_points.txt
splight_cli-5.6.2.dist-info/RECORD
