Metadata-Version: 2.4
Name: splight-cli
Version: 5.6.2
Summary: Splight Command Line Interface
Author-email: Splight Dev <dev@splight-ae.com>
Requires-Python: <4.0.0,>=3.11
Requires-Dist: case-converter==1.1.0
Requires-Dist: click-default-group==1.2.2
Requires-Dist: click==8.0.4
Requires-Dist: colorama==0.4.4
Requires-Dist: packaging==23.0
Requires-Dist: pathspec==0.11.1
Requires-Dist: py7zr==0.20.8
Requires-Dist: pyyaml==6.0.1
Requires-Dist: requests==2.32.2
Requires-Dist: rich==13.0.1
Requires-Dist: setuptools==80.7.1
Requires-Dist: splight-lib>=5.21.0
Requires-Dist: toposort<2.0,>=1.10
Requires-Dist: typer==0.15.1
